[{"id":"9rHrDrDA","hashSimple":"8eaee04bd68cb88d5b70ee7d84ee703d4679","name":"style.css.20230919-143932-d","size":4679,"createUser":"1","createTime":1695105572,"detail":""},{"id":"9p-EruOA","hashSimple":"4d71feca3fac0c9be2958fecca1c24db4616","name":"style.css.20230913-212823-4","size":4616,"createUser":"1","createTime":1694611703,"detail":""},{"id":"9p8zSYtA","hashSimple":"9c40ec8e7df9cd8c02a60a8c84212c804660","name":"style.css.20230913-190609-z","size":4660,"createUser":"1","createTime":1694603169,"detail":""},{"id":"9p8y2eeg","hashSimple":"8eaee04bd68cb88d5b70ee7d84ee703d4679","name":"style.css.20230913-190523-h","size":4679,"createUser":"1","createTime":1694603123,"detail":""}]